Metadata-Version: 2.1
Name: Watssap-web-send-message
Version: 1.0
Summary: Este pacote fornece o basico para wattsap
Author: Auto_Dev
Author-email: ramonma31@gmail.com
Keywords: wattssap,mensagem,enviar,api wattssap
License-File: license.txt
